lotf/__init__.py
lotf/core.py
lotf/lotf_ext.cpython-314t-darwin.so
lotf-0.0.4.dist-info/RECORD
lotf-0.0.4.dist-info/WHEEL
lotf-0.0.4.dist-info/METADATA
lotf-0.0.4.dist-info/licenses/LICENSE
