Metadata-Version: 2.1
Name: lotf
Version: 0.0.4
Summary: LotusFilter: Diversity-aware approximate nearest neighbor search
Author-Email: Yusuke Matsui <matsui@hal.t.u-tokyo.ac.jp>
Classifier: License :: OSI Approved :: MIT License
Project-URL: Homepage, https://github.com/matsui528/lotf
Project-URL: Documentation, https://matsui528.github.io/lotf
Requires-Python: >=3.10
Requires-Dist: numpy
Provides-Extra: docs
Requires-Dist: sphinx>=7.0; extra == "docs"
Requires-Dist: furo>=2024.1.29; extra == "docs"
Requires-Dist: myst-parser>=2.0; extra == "docs"
Requires-Dist: sphinx-autodoc-typehints>=1.25; extra == "docs"
Requires-Dist: sphinx-copybutton>=0.5; extra == "docs"
Requires-Dist: linkify-it-py>=2.0; extra == "docs"
